video_toolkits/__init__.py
video_toolkits/__version__.py
video_toolkits/core.py
video_toolkits/draw.py
video_toolkits/json_toolkits.py
video_toolkits-0.5.0.dist-info/LICENSE
video_toolkits-0.5.0.dist-info/METADATA
video_toolkits-0.5.0.dist-info/WHEEL
video_toolkits-0.5.0.dist-info/top_level.txt
video_toolkits-0.5.0.dist-info/RECORD
