Metadata-Version: 2.1
Name: video-toolkits
Version: 0.5.0
Summary: Toolkits for read/write video
Home-page: https://github.com/Celeste-cj/video_toolkits
Author: Celeste-cj
Author-email: jingc2015@pku.edu.cn
License: MIT
Classifier: License :: OSI Approved :: MIT License
Classifier: Programming Language :: Python :: 3
Classifier: Operating System :: OS Independent
Requires-Python: >=3.6.0
License-File: LICENSE
Requires-Dist: opencv-python
Requires-Dist: av
